physipy/__init__.py
physipy/_constants.py
physipy/_version.py
physipy/calculus.py
physipy/math.py
physipy/quantity/__init__.py
physipy/quantity/_numpy.py
physipy/quantity/_plot.py
physipy/quantity/_units.py
physipy/quantity/dimension.py
physipy/quantity/dimension.txt
physipy/quantity/quantity.py
physipy/quantity/utils.py
physipy-0.2.8.dist-info/licenses/LICENSE
physipy-0.2.8.dist-info/METADATA
physipy-0.2.8.dist-info/WHEEL
physipy-0.2.8.dist-info/top_level.txt
physipy-0.2.8.dist-info/RECORD
