Metadata-Version: 2.4
Name: physipy
Version: 0.2.8
Summary: Manipulate physical quantities in Python
Home-page: https://github.com/mocquin/physipy
Author: mocquin
Author-email: mocquin@me.com
License: MIT
Keywords: physics physical unit units dimension quantity quantities
License-File: LICENSE
Requires-Dist: numpy
Requires-Dist: scipy
Requires-Dist: sympy
Requires-Dist: matplotlib
Dynamic: author
Dynamic: author-email
Dynamic: description
Dynamic: description-content-type
Dynamic: home-page
Dynamic: keywords
Dynamic: license
Dynamic: license-file
Dynamic: requires-dist
Dynamic: summary
